hrm_omero/__init__.py
hrm_omero/cli.py
hrm_omero/decorators.py
hrm_omero/formatting.py
hrm_omero/hrm.py
hrm_omero/misc.py
hrm_omero/omero.py
hrm_omero/transfer.py
hrm_omero/tree.py
hrm_omero-0.4.0.dist-info/entry_points.txt
hrm_omero-0.4.0.dist-info/LICENSE
hrm_omero-0.4.0.dist-info/WHEEL
hrm_omero-0.4.0.dist-info/METADATA
hrm_omero-0.4.0.dist-info/RECORD
