Metadata-Version: 2.1
Name: hrm-omero
Version: 0.4.0
Summary: A connector between the Huygens Remote Manager (HRM) and OMERO.
Home-page: https://pypi.org/project/hrm-omero/
License: GPLv3
Keywords: hrm,huygens,omero,openmicroscopy,ome,deconvolution
Author: Niko Ehrenfeuchter
Author-email: nikolaus.ehrenfeuchter@unibas.ch
Requires-Python: >=3.6.2,<4.0.0
Classifier: License :: Other/Proprietary License
Classifier: Programming Language :: Python :: 3
Classifier: Programming Language :: Python :: 3.10
Classifier: Programming Language :: Python :: 3.7
Classifier: Programming Language :: Python :: 3.8
Classifier: Programming Language :: Python :: 3.9
Requires-Dist: Pillow (>=8.3.2,<9.0.0)
Requires-Dist: beautifulsoup4 (>=4.10.0,<5.0.0)
Requires-Dist: loguru (>=0.5.3,<0.6.0)
Requires-Dist: omero-py (>=5.9.0,<6.0.0)
Project-URL: Documentation, https://imcf.one/apidocs/hrm-omero/hrm_omero.html
Project-URL: Repository, https://github.com/imcf/hrm-omero
